{
"meta":{"test_sets":[],"test_metrics":[],"learn_metrics":[{"best_value":"Min","name":"RMSE"}],"launch_mode":"Train","parameters":"","iteration_count":100,"learn_sets":["learn"],"name":"experiment"},
"iterations":[
{"learn":[14.005006],"iteration":0,"passed_time":0.001695333542,"remaining_time":0.1678380207},
{"learn":[13.14441192],"iteration":1,"passed_time":0.002829205254,"remaining_time":0.1386310574},
{"learn":[12.34258257],"iteration":2,"passed_time":0.004634936305,"remaining_time":0.1498629405},
{"learn":[11.64527793],"iteration":3,"passed_time":0.006056322201,"remaining_time":0.1453517328},
{"learn":[11.02766183],"iteration":4,"passed_time":0.007327060951,"remaining_time":0.1392141581},
{"learn":[10.43485794],"iteration":5,"passed_time":0.008982159972,"remaining_time":0.1407205062},
{"learn":[9.890641275],"iteration":6,"passed_time":0.01100368033,"remaining_time":0.1461917529},
{"learn":[9.492161212],"iteration":7,"passed_time":0.01297731944,"remaining_time":0.1492391736},
{"learn":[9.105082953],"iteration":8,"passed_time":0.01479621498,"remaining_time":0.1496061737},
{"learn":[8.674157135],"iteration":9,"passed_time":0.01638127163,"remaining_time":0.1474314447},
{"learn":[8.341743544],"iteration":10,"passed_time":0.01755113733,"remaining_time":0.1420046566},
{"learn":[8.049372916],"iteration":11,"passed_time":0.01916753188,"remaining_time":0.1405619005},
{"learn":[7.757318612],"iteration":12,"passed_time":0.0206992783,"remaining_time":0.1385259394},
{"learn":[7.522206899],"iteration":13,"passed_time":0.02192742329,"remaining_time":0.1346970288},
{"learn":[7.297756655],"iteration":14,"passed_time":0.02303804896,"remaining_time":0.1305489441},
{"learn":[7.088359431],"iteration":15,"passed_time":0.02467026509,"remaining_time":0.1295188917},
{"learn":[6.882113791],"iteration":16,"passed_time":0.02695156315,"remaining_time":0.1315870436},
{"learn":[6.704728832],"iteration":17,"passed_time":0.02927073359,"remaining_time":0.133344453},
{"learn":[6.563881962],"iteration":18,"passed_time":0.03091449216,"remaining_time":0.1317933613},
{"learn":[6.418790279],"iteration":19,"passed_time":0.03218600124,"remaining_time":0.128744005},
{"learn":[6.315756953],"iteration":20,"passed_time":0.0333904158,"remaining_time":0.1256115642},
{"learn":[6.210157751],"iteration":21,"passed_time":0.03394069767,"remaining_time":0.1203352008},
{"learn":[6.115058449],"iteration":22,"passed_time":0.03466694507,"remaining_time":0.1160589031},
{"learn":[6.014819884],"iteration":23,"passed_time":0.03599604834,"remaining_time":0.1139874864},
{"learn":[5.93117229],"iteration":24,"passed_time":0.03749699142,"remaining_time":0.1124909743},
{"learn":[5.844857622],"iteration":25,"passed_time":0.03869645944,"remaining_time":0.1101360769},
{"learn":[5.771145213],"iteration":26,"passed_time":0.03968335137,"remaining_time":0.1072920241},
{"learn":[5.704018229],"iteration":27,"passed_time":0.04076867026,"remaining_time":0.1048337235},
{"learn":[5.665806474],"iteration":28,"passed_time":0.04194566033,"remaining_time":0.1026945477},
{"learn":[5.616500369],"iteration":29,"passed_time":0.04295378063,"remaining_time":0.1002254881},
{"learn":[5.558023666],"iteration":30,"passed_time":0.04372839591,"remaining_time":0.09733094573},
{"learn":[5.510080976],"iteration":31,"passed_time":0.04465677955,"remaining_time":0.09489565654},
{"learn":[5.468747792],"iteration":32,"passed_time":0.04565436993,"remaining_time":0.09269220562},
{"learn":[5.429275534],"iteration":33,"passed_time":0.04652109029,"remaining_time":0.09030564586},
{"learn":[5.402117324],"iteration":34,"passed_time":0.04743052889,"remaining_time":0.08808526794},
{"learn":[5.367635151],"iteration":35,"passed_time":0.04837200111,"remaining_time":0.08599466864},
{"learn":[5.345181232],"iteration":36,"passed_time":0.04928437598,"remaining_time":0.08391664018},
{"learn":[5.319151269],"iteration":37,"passed_time":0.05013048649,"remaining_time":0.08179184637},
{"learn":[5.296134146],"iteration":38,"passed_time":0.05100144223,"remaining_time":0.07977148657},
{"learn":[5.269629003],"iteration":39,"passed_time":0.0517912879,"remaining_time":0.07768693185},
{"learn":[5.251147059],"iteration":40,"passed_time":0.05260820811,"remaining_time":0.07570449459},
{"learn":[5.248003302],"iteration":41,"passed_time":0.05290490453,"remaining_time":0.07305915387},
{"learn":[5.232376509],"iteration":42,"passed_time":0.05373305101,"remaining_time":0.07122753273},
{"learn":[5.213524255],"iteration":43,"passed_time":0.05450592395,"remaining_time":0.06937117593},
{"learn":[5.189691584],"iteration":44,"passed_time":0.05536783383,"remaining_time":0.06767179691},
{"learn":[5.166052198],"iteration":45,"passed_time":0.05618983373,"remaining_time":0.06596197873},
{"learn":[5.140406659],"iteration":46,"passed_time":0.05710466048,"remaining_time":0.06439461714},
{"learn":[5.118929684],"iteration":47,"passed_time":0.05793977147,"remaining_time":0.06276808576},
{"learn":[5.108792602],"iteration":48,"passed_time":0.05863079649,"remaining_time":0.06102389023},
{"learn":[5.098141225],"iteration":49,"passed_time":0.05936374787,"remaining_time":0.05936374787},
{"learn":[5.085926393],"iteration":50,"passed_time":0.06011378745,"remaining_time":0.05775638402},
{"learn":[5.067816804],"iteration":51,"passed_time":0.0607323893,"remaining_time":0.05606066705},
{"learn":[5.049834901],"iteration":52,"passed_time":0.06141921915,"remaining_time":0.0544661},
{"learn":[5.03838627],"iteration":53,"passed_time":0.06202184665,"remaining_time":0.05283342493},
{"learn":[5.033534248],"iteration":54,"passed_time":0.06238716572,"remaining_time":0.05104404468},
{"learn":[5.023726885],"iteration":55,"passed_time":0.06296703094,"remaining_time":0.04947409574},
{"learn":[5.01290392],"iteration":56,"passed_time":0.06356808915,"remaining_time":0.04795487427},
{"learn":[5.005569127],"iteration":57,"passed_time":0.06411496967,"remaining_time":0.04642808148},
{"learn":[4.989969032],"iteration":58,"passed_time":0.06462402379,"remaining_time":0.04490821992},
{"learn":[4.976762446],"iteration":59,"passed_time":0.06510382361,"remaining_time":0.04340254907},
{"learn":[4.967222715],"iteration":60,"passed_time":0.06560884145,"remaining_time":0.04194663634},
{"learn":[4.954407599],"iteration":61,"passed_time":0.06619875637,"remaining_time":0.04057343133},
{"learn":[4.942125056],"iteration":62,"passed_time":0.06667546264,"remaining_time":0.03915860504},
{"learn":[4.930230716],"iteration":63,"passed_time":0.06719710004,"remaining_time":0.03779836877},
{"learn":[4.921695642],"iteration":64,"passed_time":0.06778154802,"remaining_time":0.03649775663},
{"learn":[4.906405625],"iteration":65,"passed_time":0.06839863462,"remaining_time":0.03523566026},
{"learn":[4.894330248],"iteration":66,"passed_time":0.06901713066,"remaining_time":0.03399351211},
{"learn":[4.88211557],"iteration":67,"passed_time":0.06965727963,"remaining_time":0.0327798963},
{"learn":[4.877946398],"iteration":68,"passed_time":0.07041133137,"remaining_time":0.03163407641},
{"learn":[4.863182126],"iteration":69,"passed_time":0.07125747854,"remaining_time":0.03053891938},
{"learn":[4.84646533],"iteration":70,"passed_time":0.07220442221,"remaining_time":0.0294919471},
{"learn":[4.838014752],"iteration":71,"passed_time":0.07312690018,"remaining_time":0.02843823896},
{"learn":[4.82981137],"iteration":72,"passed_time":0.07507855539,"remaining_time":0.02776878076},
{"learn":[4.817094767],"iteration":73,"passed_time":0.07648999482,"remaining_time":0.02687486305},
{"learn":[4.808314151],"iteration":74,"passed_time":0.07823601883,"remaining_time":0.02607867294},
{"learn":[4.796235023],"iteration":75,"passed_time":0.0797596708,"remaining_time":0.02518726446},
{"learn":[4.784434534],"iteration":76,"passed_time":0.08122537317,"remaining_time":0.02426212445},
{"learn":[4.774402487],"iteration":77,"passed_time":0.0825601383,"remaining_time":0.02328619285},
{"learn":[4.76731896],"iteration":78,"passed_time":0.08385484228,"remaining_time":0.02229052769},
{"learn":[4.75934113],"iteration":79,"passed_time":0.08525521948,"remaining_time":0.02131380487},
{"learn":[4.754106378],"iteration":80,"passed_time":0.08662403203,"remaining_time":0.02031921739},
{"learn":[4.744002932],"iteration":81,"passed_time":0.08805212255,"remaining_time":0.01932851471},
{"learn":[4.731700554],"iteration":82,"passed_time":0.08937727284,"remaining_time":0.01830618841},
{"learn":[4.723284153],"iteration":83,"passed_time":0.09042883797,"remaining_time":0.01722454057},
{"learn":[4.712232782],"iteration":84,"passed_time":0.09150142433,"remaining_time":0.01614731018},
{"learn":[4.703046867],"iteration":85,"passed_time":0.09267078538,"remaining_time":0.01508594181},
{"learn":[4.698601855],"iteration":86,"passed_time":0.09386383054,"remaining_time":0.01402562985},
{"learn":[4.692429407],"iteration":87,"passed_time":0.09503029166,"remaining_time":0.01295867614},
{"learn":[4.675027364],"iteration":88,"passed_time":0.09623283716,"remaining_time":0.01189394617},
{"learn":[4.662368584],"iteration":89,"passed_time":0.09737055249,"remaining_time":0.01081895028},
{"learn":[4.646206172],"iteration":90,"passed_time":0.0984345568,"remaining_time":0.009735285838},
{"learn":[4.641245848],"iteration":91,"passed_time":0.09945530734,"remaining_time":0.008648287595},
{"learn":[4.633900435],"iteration":92,"passed_time":0.1003285207,"remaining_time":0.007551609084},
{"learn":[4.624738236],"iteration":93,"passed_time":0.1013813746,"remaining_time":0.006471151573},
{"learn":[4.612798287],"iteration":94,"passed_time":0.1023168585,"remaining_time":0.005385097817},
{"learn":[4.605222001],"iteration":95,"passed_time":0.1032183928,"remaining_time":0.004300766366},
{"learn":[4.601725912],"iteration":96,"passed_time":0.1040642842,"remaining_time":0.003218483018},
{"learn":[4.59722371],"iteration":97,"passed_time":0.1048587712,"remaining_time":0.002139974923},
{"learn":[4.580235665],"iteration":98,"passed_time":0.1056442171,"remaining_time":0.001067113304},
{"learn":[4.57591791],"iteration":99,"passed_time":0.1064702675,"remaining_time":0}
]}